linux/__init__.py
linux/AdvancedCommands/__init__.py
linux/AdvancedCommands/ticket1.py
linux/AdvancedCommands/ticket2.py
linux/AdvancedCommands/ticket3.py
linux/AdvancedCommands/ticket4.py
linux/AdvancedCommands/ticket5.py
linux/AdvancedCommands/ticket6.py
linux/BasicCommands/__init__.py
linux/BasicCommands/ticket1.py
linux/BasicCommands/ticket2.py
linux/BasicCommands/ticket3.py
linux/Find/__init__.py
linux/Find/ticket2.py
linux/Find/ticket3.py
linux/Networking/__init__.py
linux/Networking/ticket1.py
linux/Networking/ticket2.py
linux/Networking/ticket3.py
linux/Partitions/__init__.py
linux/Partitions/ticket1.py
linux/Partitions/ticket2.py
linux/Partitions/ticket3.py
linux/Permissions/__init__.py
linux/Permissions/ticket1.py
linux/Permissions/ticket2.py
linux/Permissions/ticket3.py
linux/Storage/__init__.py
linux/Storage/ticket1.py
linux/Storage/ticket2.py
linux/Storage/ticket3.py
linux/System/__init__.py
linux/System/ticket1.py
linux/System/ticket2.py
linux/System/ticket3.py
linux/Users/__init__.py
linux/Users/ticket1.py
linux/Users/ticket2.py
linux/Users/ticket3.py
linux/shared_scripts/__init__.py
linux/shared_scripts/modules.py
linux_farrukh90-0.0.41.dist-info/LICENSE
linux_farrukh90-0.0.41.dist-info/METADATA
linux_farrukh90-0.0.41.dist-info/WHEEL
linux_farrukh90-0.0.41.dist-info/top_level.txt
linux_farrukh90-0.0.41.dist-info/RECORD
